{"expansion":{"name":"Humanity Hates the Holidays \"Love\" Edition"},"white_cards":{"17072":{"text":"(An) eggplant emoji."},"17073":{"text":"100% All-Beef Thermometer."},"17074":{"text":"8th Grade and Pregnant."},"17075":{"text":"A \"Happy Valentine's Day\" Card from AshleyMadison.com."},"17076":{"text":"A gas station teddy bear."},"17077":{"text":"A peanut butter and KY Jelly sandwich."},"17078":{"text":"A sex doll that just wants to be friends."},"17079":{"text":"Abortion Baby Shower."},"17080":{"text":"Accidentally hitching a ride on the bang bus."},"17081":{"text":"Accidentally sexting your mom."},"17082":{"text":"Ashley Madison & Chill."},"17083":{"text":"Awkwardly confessing your love via text."},"17084":{"text":"Bananas, Cucumbers, and Hot Dogs."},"17085":{"text":"Being a sidechick on Valentine's Day."},"17086":{"text":"Bleeding Dick."},"17087":{"text":"Bringing your sidekick to your Valentine's Date."},"17088":{"text":"Buying candy and stuffed animals on sale on February 15th."},"17089":{"text":"Claiming Russell Stover\u2122 as your Valentine."},"17090":{"text":"Clown Fucking."},"17091":{"text":"Congratulating someone on the results of their unprotected sex."},"17092":{"text":"Convoncing your mom to Google \"Lemon Party\"."},"17093":{"text":"Dad's used fleshlight."},"17094":{"text":"Dating a senior."},"17095":{"text":"Designated Ugly Fat Friend."},"17096":{"text":"Diaper Fetishes."},"17097":{"text":"Downloading Grindr\u2122 on Valentine's Day to \"check it out\"."},"17098":{"text":"Eating an entire box of chocolates."},"17099":{"text":"Fake male orgasms."},"17100":{"text":"Finding your mother's special lingerie...on your dad."},"17101":{"text":"Giving out Valentine handjobs."},"17102":{"text":"Gluten-free edible panties."},"17103":{"text":"Grabbing her by the pussy."},"17104":{"text":"Haivng sex on the display beds at Sears."},"17105":{"text":"Having a surprise baby on November 14th."},"17106":{"text":"Having Maury Povich tell you, \"You are not the father\"."},"17107":{"text":"Hearing your dad offer to give your mom his special cream pie."},"17108":{"text":"Heat-Seeking Love Missile."},"17109":{"text":"Helping someone move and finding a giant bag of sex toys."},"17110":{"text":"Inappropriate Valentine's Day cards in your kid's classroom."},"17111":{"text":"Jelly Bean Shits."},"17112":{"text":"Jerking off to Fraggle Rock."},"17113":{"text":"Leaving a sex partner so dissatisfied that you regain your virginity."},"17114":{"text":"Looking at my sister's face under a blacklight."},"17115":{"text":"Losing your v-card on V-Day."},"17116":{"text":"Love Muscle."},"17117":{"text":"Making her squirt farther than a Super Soaker\u2122."},"17118":{"text":"Milking the family snake."},"17119":{"text":"Moms riding motorcycles."},"17120":{"text":"Mr. Happy."},"17121":{"text":"My brother's special sock."},"17122":{"text":"OkCupid\u2122."},"17123":{"text":"Ordering enough Valentine's Day takeout for 2 people to avoid the delivery guy's pity."},"17124":{"text":"Overindulging on gummy bears."},"17125":{"text":"Panties so moist they could drown a beaver."},"17126":{"text":"Placing burning cigarettes in your spouse's purse."},"17127":{"text":"Practicing Cosmopolitan's 50 naughty V-Day moves."},"17128":{"text":"Proposing to your sidechick accidentally."},"17129":{"text":"Re-inventing what it means to \"Doggy-Style\"."},"17130":{"text":"Ripping out anal beads like you're starting a lawnmower."},"17131":{"text":"Semen-flavored truffles."},"17132":{"text":"Sending yourself flowers."},"17133":{"text":"Seven minutes in heaven."},"17134":{"text":"Single's awareness day."},"17135":{"text":"Stop & Frisk Role-Playing."},"17136":{"text":"Stripper's Clothes."},"17137":{"text":"Surprise Anal."},"17138":{"text":"Switching out Valentines for dog shit."},"17139":{"text":"Tens, Tens, Tens, Twenties on my Twitties."},"17140":{"text":"The desparate girl who wanted to be a mom so bad that she robbed a sperm bank."},"17141":{"text":"The hospital baby swap."},"17142":{"text":"The morning after pill."},"17143":{"text":"Throwing rolls of pennies at strippers."},"17144":{"text":"Trying to take her bra off with one hand."},"17145":{"text":"Turbo thots."},"17146":{"text":"Using a suicide hotline for phone sex."},"17147":{"text":"Valentine's Day, when delivery guys make more than just tips."},"17148":{"text":"Walking in on your sister using your electric toothbrush."},"17149":{"text":"Whitening your teeth with Dad's help."},"17150":{"text":"Your boyfriend revealing Cupid isn't the only fairy on Valentine's Day."},"17151":{"text":"Your father's porn collection."}},"black_cards":{"4623":{"text":"_ is the key to recovery.","pick":1},"4624":{"text":"Believe in the magic of _.","pick":1},"4625":{"text":"Can you feel the _ tonight?","pick":1},"4626":{"text":"Cupid is known for this _.","pick":1},"4627":{"text":"Every kiss begins with _.","pick":1},"4628":{"text":"Getting drunk on Valentine's Day usually leads to _.","pick":1},"4629":{"text":"He got harder than a rock afeter he saw _.","pick":1},"4630":{"text":"I can't believe he proposed to me with _ instead of a ring.","pick":1},"4631":{"text":"I can't believe my sister wrote in her diary about _.","pick":1},"4632":{"text":"I found my mom's dildo and traded it for _.","pick":1},"4633":{"text":"I gave my girlfriend a B- because she didn't use (a\/the) _.","pick":1},"4634":{"text":"I hate Cupid because (of) _.","pick":1},"4635":{"text":"I love you more than _.","pick":1},"4636":{"text":"If you thought American Pie was bad, you should have seen what I did with _.","pick":1},"4637":{"text":"Instead of roses, he gave me _.","pick":1},"4638":{"text":"My girlfriend gave me chocolate-covered _.","pick":1},"4639":{"text":"Only you can prevent _.","pick":1},"4640":{"text":"Our waitress at Hooters\u2122 showed us her _.","pick":1},"4641":{"text":"Our wedding night consisted of _ and _.","pick":2},"4642":{"text":"Roses are red,\nViolets are blue,\nI am going to _\nwith you.","pick":1},"4643":{"text":"Sex: Making _ great again.","pick":1},"4644":{"text":"She just got a new tramp stamp of _.","pick":1},"4645":{"text":"St. Valentine: Patron Saint of _.","pick":1},"4646":{"text":"The Cosmo-sex-act-of-the-month: _. Surprise him with it tonight!","pick":1},"4647":{"text":"The true meaning of love is _.","pick":1},"4648":{"text":"To prove he loved me, he gave me _.","pick":1},"4649":{"text":"What can _ do for you?","pick":1},"4650":{"text":"What Cinderella really asked of her Fairy Godmother is _.","pick":1},"4651":{"text":"When you run out of Valentine's Day gift ideas, you should get _.","pick":1},"4652":{"text":"Why do I like you?","pick":1}}}