{"expansion":{"name":"Kids Against Maturity"},"white_cards":{"17357":{"text":"#Hashtag"},"17358":{"text":"20,000 Leagues Under the Sea\u2122"},"17359":{"text":"A dirty Q-Tip\u2122"},"17360":{"text":"A fat sports analyst"},"17361":{"text":"a hole"},"17362":{"text":"A pinata full of baked beans"},"17363":{"text":"A Plunger"},"17364":{"text":"A sponge"},"17365":{"text":"A teaspoon full of toenail clippings"},"17366":{"text":"A three legged tiger chasing a gazelle"},"17367":{"text":"A turd burglar"},"17368":{"text":"A turkey baster"},"17369":{"text":"A unicorn farting rainbows"},"17370":{"text":"A years supply of turkey jerky"},"17371":{"text":"Achy breaky mullets"},"17372":{"text":"After concert morning voice"},"17373":{"text":"Alien probing"},"17374":{"text":"All hail the sofa king!"},"17375":{"text":"An entire day without using the internet"},"17376":{"text":"Atomic wedgies"},"17377":{"text":"Awesome sauce"},"17378":{"text":"Awkwardly getting caught sitting next to my sibling on the kiss cam"},"17379":{"text":"Back boobs"},"17380":{"text":"Backpack burrito"},"17381":{"text":"Bacon strips"},"17382":{"text":"Bag of pickled pigs feet"},"17383":{"text":"Baking an air muffin"},"17384":{"text":"Baking brownies"},"17385":{"text":"Banana hammock"},"17386":{"text":"Bangkok"},"17387":{"text":"Barking spiders"},"17388":{"text":"Bat wings"},"17389":{"text":"Bearded lady"},"17390":{"text":"Bees knees"},"17391":{"text":"Being poned"},"17392":{"text":"Big butts"},"17393":{"text":"Biscuits n' gravy"},"17394":{"text":"Blackbeard"},"17395":{"text":"Boobs"},"17396":{"text":"Boogers"},"17397":{"text":"Brain kernels in zombie poop"},"17398":{"text":"Brown clowns"},"17399":{"text":"Bubble Guppies\u2122"},"17400":{"text":"Bung-O the clown"},"17401":{"text":"Burpees"},"17402":{"text":"Burping out candles"},"17403":{"text":"Butt bingo"},"17404":{"text":"Butt flood"},"17405":{"text":"Butt lovers pizza"},"17406":{"text":"Butt thermometer"},"17407":{"text":"Camel toenail"},"17408":{"text":"Camp Dickie-doo"},"17409":{"text":"Captain America's\u2122 shield"},"17410":{"text":"Captain Obvious"},"17411":{"text":"Captain Underpants"},"17412":{"text":"Captain's Crunch"},"17413":{"text":"Captain's log"},"17414":{"text":"Care Bear stares"},"17415":{"text":"Cat litter"},"17416":{"text":"Cat Man Do"},"17417":{"text":"Cat puke between your toes"},"17418":{"text":"Chafed nippers"},"17419":{"text":"Cheesy poofs\u2122"},"17420":{"text":"Chewbacaa's dingleberries"},"17421":{"text":"Chicken butt"},"17422":{"text":"Chicken thigh"},"17423":{"text":"Chili dogs"},"17424":{"text":"Chocolate bar floating in a pool"},"17425":{"text":"Chunky milk"},"17426":{"text":"Clifford the Big Red Dog's\u2122 big brown log"},"17427":{"text":"Cooked pizza rolls with a frozen center"},"17428":{"text":"Cool beans"},"17429":{"text":"Crop dusting"},"17430":{"text":"Cute cat videos"},"17431":{"text":"Dad's hemorroid pad"},"17432":{"text":"Dad's special microwave dinner"},"17433":{"text":"Daddy's listening skills"},"17434":{"text":"Diarrhea cha cha cha"},"17435":{"text":"Dingle and the berries"},"17436":{"text":"Dingus"},"17437":{"text":"Dirt button"},"17438":{"text":"DJ Lance\u2122"},"17439":{"text":"Dog farts"},"17440":{"text":"Dr. Doo Doo Brown"},"17441":{"text":"Drake and Young Jeezy sharing a milkshake"},"17442":{"text":"Duck lips"},"17443":{"text":"Dung beetle"},"17444":{"text":"Dust bunnies"},"17445":{"text":"Eating a firefly to make your teeth glow"},"17446":{"text":"Electric Avenue"},"17447":{"text":"Everything is awesome!"},"17448":{"text":"Fake lottery tickets"},"17449":{"text":"Fanny packs"},"17450":{"text":"Fart in a space suit"},"17451":{"text":"Fart in the car. Lock the windows. Turn on the heat. Enjoy."},"17452":{"text":"Fart tennis"},"17453":{"text":"Fartknockers"},"17454":{"text":"Farts in a throw pillow"},"17455":{"text":"Fat guy in a little coat"},"17456":{"text":"Fat lady in yoga pants"},"17457":{"text":"Fat shaming"},"17458":{"text":"Feces pieces"},"17459":{"text":"Feeding baby bird style"},"17460":{"text":"Finger painting"},"17461":{"text":"Flaming bag of poop on my front porch"},"17462":{"text":"Free doodie"},"17463":{"text":"Frog farts"},"17464":{"text":"Fromunda cheese"},"17465":{"text":"Front farts"},"17466":{"text":"Front wedgies"},"17467":{"text":"Fruit boots"},"17468":{"text":"Fudgesicles"},"17469":{"text":"Full-on battle beast mode"},"17470":{"text":"Funkytown"},"17471":{"text":"Funny smell of grandma's house"},"17472":{"text":"Gallons of melted Velveeta\u2122"},"17473":{"text":"Getting hit below the belt with a football"},"17474":{"text":"Getting ready to get ready"},"17475":{"text":"Gogurt burps"},"17476":{"text":"Grandma's jitterbug phone"},"17477":{"text":"Grouchland"},"17478":{"text":"Grumpy cats"},"17479":{"text":"Grumpy munchkins"},"17480":{"text":"Gum in the hair"},"17481":{"text":"Helping your grandparent get dressed"},"17482":{"text":"Hershey\u2122 and the squirts"},"17483":{"text":"Hershey\u2122 highway"},"17484":{"text":"Hillary Duff"},"17485":{"text":"Hollywood dreams"},"17486":{"text":"Honey badger"},"17487":{"text":"Hoof hearted"},"17488":{"text":"Hot Pockets\u2122"},"17489":{"text":"Hulk smashed"},"17490":{"text":"Human beans"},"17491":{"text":"Humble brags"},"17492":{"text":"Hungry + Angry = Hangry"},"17493":{"text":"In a van down by the river"},"17494":{"text":"In your face"},"17495":{"text":"Inflatable dart boards"},"17496":{"text":"Itchy bum"},"17497":{"text":"Jar of egg farts"},"17498":{"text":"Jenga\u2122 tower made of cheese sticks"},"17499":{"text":"John Cena"},"17500":{"text":"Justin Bieber"},"17501":{"text":"Katy Perry's new boyfriend"},"17502":{"text":"Kim Kardashian's booty"},"17503":{"text":"Kindergarten cops"},"17504":{"text":"Kittens in mittens"},"17505":{"text":"Knuckle sandwiches"},"17506":{"text":"Lady Gaga"},"17507":{"text":"Lazy Sunday"},"17508":{"text":"Lebron James' size 15 shoe"},"17509":{"text":"Like a bo$$"},"17510":{"text":"Luke Skywalkers\u2122 robot hand"},"17511":{"text":"Magic Mushrooms"},"17512":{"text":"Mandatory family time"},"17513":{"text":"Manties"},"17514":{"text":"Master splinter"},"17515":{"text":"Mayor McCheeze's\u2122 cheese tongue"},"17516":{"text":"Meatlofa! The world's first meatloaf sofa"},"17517":{"text":"Mexican mudslide"},"17518":{"text":"Miley Cyrus"},"17519":{"text":"Mom is pregnant again"},"17520":{"text":"Mom's purple wine teeth"},"17521":{"text":"Moobs"},"17522":{"text":"Moose knuckles"},"17523":{"text":"Mouth breathers"},"17524":{"text":"Mr Weird Beard"},"17525":{"text":"Mr. Froto's ring"},"17526":{"text":"Mr. Maigi"},"17527":{"text":"Mr. Poopeedoopee"},"17528":{"text":"Mr. Richard Johnson"},"17529":{"text":"My cat's starfish"},"17530":{"text":"My cellphone after landing in the toilet"},"17531":{"text":"My Dad's back hair"},"17532":{"text":"My dog's lipstick"},"17533":{"text":"My entire high school football team"},"17534":{"text":"Mystery egg wrapped in Play-Doh\u2122"},"17535":{"text":"Mystery hair on my donut"},"17536":{"text":"Nahrwals"},"17537":{"text":"Neck beards"},"17538":{"text":"Nick Jonas\u2122"},"17539":{"text":"Nicki Minaj"},"17540":{"text":"Ninja bread men"},"17541":{"text":"Oompa-Loompas\u2122"},"17542":{"text":"Optimus Prime's\u2122 exhaust pipe"},"17543":{"text":"Pee on the seat"},"17544":{"text":"Pee pee tee pee"},"17545":{"text":"Peeing in the shower"},"17546":{"text":"Peeing my name in the snow"},"17547":{"text":"Pepperfarts"},"17548":{"text":"Pickle juice"},"17549":{"text":"Pinch a loaf"},"17550":{"text":"Pink poodles eating oodles of noodles"},"17551":{"text":"Plump pageant moms"},"17552":{"text":"Poop emoji"},"17553":{"text":"Poop spelled backwards"},"17554":{"text":"Poops Mcgee"},"17555":{"text":"Puckered starfish"},"17556":{"text":"Pull my finger"},"17557":{"text":"Purple nurples"},"17558":{"text":"R2D2\u2122"},"17559":{"text":"Rainbow Dash\u2122 droppings"},"17560":{"text":"Rotten eggs"},"17561":{"text":"Rubber baby buggy bumpers"},"17562":{"text":"Sad pancakes"},"17563":{"text":"Sand in the cheeks"},"17564":{"text":"Santa's big fat sack"},"17565":{"text":"Sasquatch"},"17566":{"text":"Scooby snacks\u2122"},"17567":{"text":"Sea biscuit"},"17568":{"text":"Secret crush announced on the school P.A."},"17569":{"text":"Selfie fail"},"17570":{"text":"Selfie sticks"},"17571":{"text":"Sesame Street\u2122"},"17572":{"text":"Shark sugar"},"17573":{"text":"Shart tank"},"17574":{"text":"Shaving"},"17575":{"text":"Shopkinz\u2122"},"17576":{"text":"Sloth's Baby Ruth\u2122"},"17577":{"text":"Smurf Village"},"17578":{"text":"Snapchatting in your sleep"},"17579":{"text":"Sneaky snakes"},"17580":{"text":"Spagooter"},"17581":{"text":"Spongebob's square poop"},"17582":{"text":"Squeeze cheese"},"17583":{"text":"Stranger danger"},"17584":{"text":"Sugar Bear\u2122"},"17585":{"text":"Super Mario\u2122 fart"},"17586":{"text":"Superman's\u2122 skid marks"},"17587":{"text":"Taco Tuesday"},"17588":{"text":"Taylor Swift"},"17589":{"text":"Teacher crush"},"17590":{"text":"That dream where I am at school naked"},"17591":{"text":"That kid that never stopped eating paste"},"17592":{"text":"The babysitter's\u2122 boyfriend"},"17593":{"text":"The bully that never wears deodorant"},"17594":{"text":"The day I got a wedgie and forgot to wipe properly"},"17595":{"text":"The Gooch"},"17596":{"text":"The janitor's vomit dust"},"17597":{"text":"The kid who pooped their pants on the bus"},"17598":{"text":"The kid who wipes boogers under the desk"},"17599":{"text":"The Ol'courtesy flush"},"17600":{"text":"The rabbit hole"},"17601":{"text":"Thor's hammer time"},"17602":{"text":"Those kooky people that live downstairs"},"17603":{"text":"Throbbing zit on picture day"},"17604":{"text":"Tighty whitie underpants"},"17605":{"text":"Tipped over Port-O-Potty"},"17606":{"text":"Toilet paper"},"17607":{"text":"Triple rainbow"},"17608":{"text":"Twinkle toes"},"17609":{"text":"Underoos\u2122"},"17610":{"text":"Underwear"},"17611":{"text":"Upside down frowns"},"17612":{"text":"Uranus - The brown planet"},"17613":{"text":"Urethra Franklin"},"17614":{"text":"Used toilet paper"},"17615":{"text":"Using poison ivy to wipe your butt"},"17616":{"text":"Wacky tobacky"},"17617":{"text":"Walt Disney's secret vault"},"17618":{"text":"Wax lips"},"17619":{"text":"Wet farts"},"17620":{"text":"Wet wipes"},"17621":{"text":"Whoflungpoo"},"17622":{"text":"Wicked step sisters"},"17623":{"text":"Wiener dogs"},"17624":{"text":"Winnie's poo"},"17625":{"text":"Wolfman's nards"},"17626":{"text":"Woopy cushions"},"17627":{"text":"Yellow snow"},"17628":{"text":"Your mom after she's read Lady Chatterly's Lover"}},"black_cards":{"4698":{"text":"_ _ go away. Come back another day.","pick":2},"4699":{"text":"_ gives Dad bad gas.","pick":1},"4700":{"text":"_ invented time travel.","pick":1},"4701":{"text":"_ is the secrt ingredient in Grandma's famous pies.","pick":1},"4702":{"text":"#1 topic discussed in your teacher's lounge _.","pick":1},"4703":{"text":"A _ in the hand is worth two in the bush.","pick":1},"4704":{"text":"After being crowned homecoming king or queen, your first dance is interrupted by _.","pick":1},"4705":{"text":"All day I dream about _.","pick":1},"4706":{"text":"All dogs go to _.","pick":1},"4707":{"text":"All we are saying is give _a chance.","pick":1},"4708":{"text":"At a parent teacher conference, your teacher confessed you have a serious problem focusing on _.","pick":1},"4709":{"text":"At the end of the day, my underwear is so _ in the front and _ in the back.","pick":2},"4710":{"text":"Beauty and the _.","pick":1},"4711":{"text":"Brussel sprouts taste like _.","pick":1},"4712":{"text":"Cat in the _.","pick":1},"4713":{"text":"Charlie and the chocolate _.","pick":1},"4714":{"text":"Cloudy with a chance of _.","pick":1},"4715":{"text":"Diary of a wimpy _.","pick":1},"4716":{"text":"Do not _ on my parade.","pick":1},"4717":{"text":"Does a bear _ in the woods?","pick":1},"4718":{"text":"Dude, where's my _?","pick":1},"4719":{"text":"During the family vacation I found a _ washed up on the beach.","pick":1},"4720":{"text":"Eenie, meenie, miney, _.","pick":1},"4721":{"text":"EEWWWW! There is _ in my shoes.","pick":1},"4722":{"text":"Fast food restaurants have decided to add _ to make kids meals healthier for kids.","pick":1},"4723":{"text":"Find a _ and pick it up, and all the day you'll have good luck.","pick":1},"4724":{"text":"For Halloween I dressed as _.","pick":1},"4725":{"text":"For my birthday _ jumped out of my cake.","pick":1},"4726":{"text":"Grandma got run over by a _.","pick":1},"4727":{"text":"Grandpa says \"When I was your age we would _ for fun\".","pick":1},"4728":{"text":"Green eggs and _.","pick":1},"4729":{"text":"Happy Birthday to _.","pick":1},"4730":{"text":"Harry Potter\u2122 and the Goblet of _.","pick":1},"4731":{"text":"Help! My dog just _.","pick":1},"4732":{"text":"Here is the church, here is the steeple. Flip it over and here are the _.","pick":1},"4733":{"text":"Hey diddle diddle the _ and the fiddle, the _ jumped over the moon.","pick":2},"4734":{"text":"Hey everybody! I just won the _ eating contest.","pick":1},"4735":{"text":"Hobbit's feet smell like _.","pick":1},"4736":{"text":"How much _ can a woodchuck chuck?","pick":1},"4737":{"text":"How much is that _ in the window?","pick":1},"4738":{"text":"How the _ stole Christmas.","pick":1},"4739":{"text":"Humpty Dumpty sat on _.","pick":1},"4740":{"text":"I asked for _ for Christmas.","pick":1},"4741":{"text":"I bumped my head so hard I woke up and thought I was _!","pick":1},"4742":{"text":"I flushed my dead _ down the toilet.","pick":1},"4743":{"text":"I found _ in my cupcake.","pick":1},"4744":{"text":"I found _ in Papa Smurf's beard.","pick":1},"4745":{"text":"I found a _ in my bellybutton, and named it _.","pick":2},"4746":{"text":"I got catfished by a _ again!","pick":1},"4747":{"text":"I got stuck in time out for _.","pick":1},"4748":{"text":"I just built a rocket ship out of _.","pick":1},"4749":{"text":"I like to brush my teeth with  _.","pick":1},"4750":{"text":"I love you to the _ and back.","pick":1},"4751":{"text":"I pledge allegiance to the _.","pick":1},"4752":{"text":"I posted a picture of _ and crashed the internet.","pick":1},"4753":{"text":"I sneezed so hard _ came out my nose.","pick":1},"4754":{"text":"I spy with my little eye something _.","pick":1},"4755":{"text":"I went to my parent's closet to look for Christmas presents only to find _.","pick":1},"4756":{"text":"I will huff and puff and blow your _ down.","pick":1},"4757":{"text":"I will huff and puff, and blow your _ down!","pick":1},"4758":{"text":"If you rub a unicorn horn you will receive _.","pick":1},"4759":{"text":"It's a bird! It's a plane! No it's _!","pick":1},"4760":{"text":"Just a spoon full of _ helps the medicine go down.","pick":1},"4761":{"text":"Kill two birds with one _.","pick":1},"4762":{"text":"Knock, knock.\nWhos there?\n_.","pick":1},"4763":{"text":"Lady and the _.","pick":1},"4764":{"text":"Last night I found _ in my bed.","pick":1},"4765":{"text":"Let all play Paper, Scissors, _.","pick":1},"4766":{"text":"Let's go to the movies and see _.","pick":1},"4767":{"text":"Liar liar pants on _.","pick":1},"4768":{"text":"Little Boy Blue go blow your _.","pick":1},"4769":{"text":"Luke, I am your _.","pick":1},"4770":{"text":"Mary had a little _.","pick":1},"4771":{"text":"May I have your attention please! _. That is all.","pick":1},"4772":{"text":"May the _ be with you.","pick":1},"4773":{"text":"Milk milk lemonade, around the corner _ is made.","pick":1},"4774":{"text":"Mom says I'mnot allowed to play with _.","pick":1},"4775":{"text":"My brother his my markers in _.","pick":1},"4776":{"text":"My Dad walks in my bedroom and says \"It's time we talk about _\".","pick":1},"4777":{"text":"My favorite after school snack is _.","pick":1},"4778":{"text":"My favorite after school subject is _.","pick":1},"4779":{"text":"My favorite cartoon is _.","pick":1},"4780":{"text":"My favorite drink is _.","pick":1},"4781":{"text":"My favorite Pokemon\u2122character is _.","pick":1},"4782":{"text":"My favorite thing to read about is _.","pick":1},"4783":{"text":"My Grandpa always says \"You can't have _ if you do not eat your _\".","pick":2},"4784":{"text":"My imaginary friend's name is _.","pick":1},"4785":{"text":"My Mom ran over _ with the mini van.","pick":1},"4786":{"text":"My Mom sent me to the grocery store to pick up _.","pick":1},"4787":{"text":"My mom's cooking tastes like _.","pick":1},"4788":{"text":"My Mom's farts smell like _.","pick":1},"4789":{"text":"My parents always make me _ before school.","pick":1},"4790":{"text":"My parents order chinese food for dinner, and I open the box only to find _ in my food.","pick":1},"4791":{"text":"My teacher pulls me aside to propose that I switch to a school specifically for _.","pick":1},"4792":{"text":"Never eat soggy _.","pick":1},"4793":{"text":"Never take candy from _.","pick":1},"4794":{"text":"No more _ jumping on the bed.","pick":1},"4795":{"text":"On my summer vacation I went to _ and I saw _.","pick":2},"4796":{"text":"One _, two _, red _, blue _.","pick":4},"4797":{"text":"Peace, Love, _.","pick":1},"4798":{"text":"Peter piper picked a peck of pickled _.","pick":1},"4799":{"text":"Puff the Magic _.","pick":1},"4800":{"text":"Sally sold sea shells down by the _.","pick":1},"4801":{"text":"Say hello to my little _!","pick":1},"4802":{"text":"School was canceled because of _ again.","pick":1},"4803":{"text":"Silly rabbit _ are for kids.","pick":1},"4804":{"text":"Snap crackle and _.","pick":1},"4805":{"text":"Step on a crack and you will break your mother's back _.","pick":1},"4806":{"text":"Stop drop and _.","pick":1},"4807":{"text":"Sugar and spice and everything _.","pick":1},"4808":{"text":"Teenage Mutant Ninja _.","pick":1},"4809":{"text":"The amazing adventures of Captain Toad and _.","pick":1},"4810":{"text":"The batmobile lost a _ and the Joker got away!","pick":1},"4811":{"text":"The emperor's new _.","pick":1},"4812":{"text":"The little _ that could.","pick":1},"4813":{"text":"The moon is made of _.","pick":1},"4814":{"text":"The President just declared _ as a national treasure.","pick":1},"4815":{"text":"The toilet is clogged with _.","pick":1},"4816":{"text":"The tooth fairy left a _ under my pillow.","pick":1},"4817":{"text":"There is a place in France where the naked ladies dance. There is a hole in the wall where the men can see _.","pick":1},"4818":{"text":"This is my favorite thing to bring to a party.","pick":1},"4819":{"text":"This looks like a job for _.","pick":1},"4820":{"text":"This one time... at band camp... I saw my best friend _.","pick":1},"4821":{"text":"To infinity and _!","pick":1},"4822":{"text":"Trick or treat smell my _.","pick":1},"4823":{"text":"Up your nose with a rubber _.","pick":1},"4824":{"text":"Wait 30 minutes to swim after _.","pick":1},"4825":{"text":"Watch me whip. Watch me _.","pick":1},"4826":{"text":"We all live in a yellow _.","pick":1},"4827":{"text":"We learned about _ in school today.","pick":1},"4828":{"text":"We ran out of toilet paper, so I had to use _.","pick":1},"4829":{"text":"What does the fox say? _.","pick":1},"4830":{"text":"What is in Polly's pockets?","pick":1},"4831":{"text":"What is the new unofficial mascot of the Coast Guard?","pick":1},"4832":{"text":"What's in Puss's boots?","pick":1},"4833":{"text":"Wheels on the bus go _ and _.","pick":2},"4834":{"text":"When I eat asparagus, my pee smells like _.","pick":1},"4835":{"text":"When I grow up, I want to be a _.","pick":1},"4836":{"text":"Where in the world is _?","pick":1},"4837":{"text":"Where in the world is _?","pick":1},"4838":{"text":"Which came first, the chicken or the _?","pick":1},"4839":{"text":"Who ate my _ again?","pick":1},"4840":{"text":"Who lives in a pineapple under the sea? _!","pick":1},"4841":{"text":"Who you gonna call?","pick":1},"4842":{"text":"Whos afraid of the big bad _.","pick":1},"4843":{"text":"Why do I feel so dizzy?","pick":1},"4844":{"text":"Why is the sky blue?","pick":1},"4845":{"text":"www._.com","pick":1},"4846":{"text":"Yankee Doodle went to town riding on a _ stuck a feather in his _ and called it macaroni.","pick":2},"4847":{"text":"You ain't never had a _ like me!","pick":1},"4848":{"text":"You are under arrest for _, again!","pick":1}}}